blackfynn-collection-downloader/__init__.py
blackfynn-collection-downloader/config.py
blackfynn-collection-downloader/main.py
blackfynn-collection-downloader/ui.py
collectiondbf/__init__.py
collectiondbf/__main__.py
collectiondbf/command_line.py
collectiondbf/config.py
collectiondbf/ui.py
collectiondbf-0.1.4.dist-info/METADATA
collectiondbf-0.1.4.dist-info/WHEEL
collectiondbf-0.1.4.dist-info/top_level.txt
collectiondbf-0.1.4.dist-info/RECORD
