Metadata-Version: 2.1
Name: collectiondbf
Version: 0.1.4
Summary: Download all files in a Blackfynn collection via command line or gui
Home-page: https://github.com/tehsurfer/collectiondbf
Author: Jesse Khorasanee
Author-email: jessekhorasanee@gmail.com
License: UNKNOWN
Platform: UNKNOWN
Classifier: Development Status :: 3 - Alpha
Classifier: Programming Language :: Python :: 3.4
Classifier: Programming Language :: Python :: 3.5
Classifier: Programming Language :: Python :: 3.6
Classifier: Programming Language :: Python :: 3.7
Classifier: License :: OSI Approved :: MIT License
Classifier: Operating System :: OS Independent
Classifier: Intended Audience :: Science/Research
Requires-Python: >=3.3
Requires-Dist: blackfynn
Requires-Dist: requests
Requires-Dist: progressbar2
